taskmaster/__init__.py
taskmaster/service.py
taskmaster/taskmaster.py
taskmaster/gui/__init__.py
taskmaster/gui/_configuration.py
taskmaster/gui/_default.py
taskmaster/gui/_log.py
taskmaster/gui/_services.py
taskmaster/gui/_utils.py
taskmaster/gui/gui.py
taskmaster/gui/table.py
taskmaster/utils/__init__.py
taskmaster/utils/config.py
taskmaster/utils/email.py
taskmaster/utils/log_reader.py
taskmaster/utils/logger.py
42_taskmaster-1.0.2.dist-info/METADATA
42_taskmaster-1.0.2.dist-info/WHEEL
42_taskmaster-1.0.2.dist-info/entry_points.txt
42_taskmaster-1.0.2.dist-info/top_level.txt
42_taskmaster-1.0.2.dist-info/RECORD
