Metadata-Version: 2.1
Name: 42-taskmaster
Version: 1.0.2
Summary: A process manager project for 42
Author-email: Timothee Lafay <tlafay@student.42lyon.fr>, Theo Nard <tnard@student.42lyon.fr>
Classifier: Programming Language :: Python :: 3
Classifier: Operating System :: Unix
Requires-Python: >=3.11
Requires-Dist: Cerberus ==1.3.5
Requires-Dist: PyYAML ==6.0.1
